[{"actualEventTimestamp":"2021-03-23T16:09:18.213436Z","eventName":"INITIALIZE_SCENARIO"},{"actualEventTimestamp":"2021-03-23T16:09:18.5929234Z","eventName":"OrderStatusChangedToPaidIntegrationEvent"},{"actualEventTimestamp":"2021-03-23T16:09:20.7286841Z","eventName":"ProductPriceChangedIntegrationEvent"},{"actualEventTimestamp":"2021-03-23T16:09:20.8992263Z","eventName":"ProductPriceChangedIntegrationEvent"},{"actualEventTimestamp":"2021-03-23T16:09:21.569472500Z","eventName":"EXECUTE_SCENARIO"},{"actualEventTimestamp":"2021-03-23T16:09:21.569058200Z","eventName":"EXECUTE_SCENARIO"},{"actualEventTimestamp":"2021-03-23T16:09:21.569058200Z","eventName":"EXECUTE_SCENARIO"},{"actualEventTimestamp":"2021-03-23T16:09:21.569058200Z","eventName":"EXECUTE_SCENARIO"},{"actualEventTimestamp":"2021-03-23T16:09:21.593423100Z","eventName":"EXECUTE_SCENARIO"},{"actualEventTimestamp":"2021-03-23T16:09:21.593423100Z","eventName":"EXECUTE_SCENARIO"},{"actualEventTimestamp":"2021-03-23T16:09:21.585001500Z","eventName":"EXECUTE_SCENARIO"},{"actualEventTimestamp":"2021-03-23T16:09:21.593423100Z","eventName":"EXECUTE_SCENARIO"},{"actualEventTimestamp":"2021-03-23T16:09:21.603800Z","eventName":"EXECUTE_SCENARIO"},{"actualEventTimestamp":"2021-03-23T16:09:21.603800Z","eventName":"EXECUTE_SCENARIO"},{"actualEventTimestamp":"2021-03-23T16:09:21.6686263Z","eventName":"OrderStatusChangedToPaidIntegrationEvent"},{"actualEventTimestamp":"2021-03-23T16:09:23.3542008Z","eventName":"OrderStatusChangedToPaidIntegrationEvent"},{"actualEventTimestamp":"2021-03-23T16:09:23.6651569Z","eventName":"OrderStatusChangedToPaidIntegrationEvent"},{"actualEventTimestamp":"2021-03-23T16:09:25.2298735Z","eventName":"OrderStatusChangedToPaidIntegrationEvent"},{"actualEventTimestamp":"2021-03-23T16:09:25.575038Z","eventName":"OrderStatusChangedToPaidIntegrationEvent"},{"actualEventTimestamp":"2021-03-23T16:09:27.4000292Z","eventName":"OrderStatusChangedToPaidIntegrationEvent"},{"actualEventTimestamp":"2021-03-23T16:09:21.0280743Z","eventName":"UserCheckoutAcceptedIntegrationEvent"},{"actualEventTimestamp":"2021-03-23T16:09:21.0279757Z","eventName":"UserCheckoutAcceptedIntegrationEvent"},{"actualEventTimestamp":"2021-03-23T16:09:21.0368485Z","eventName":"UserCheckoutAcceptedIntegrationEvent"},{"actualEventTimestamp":"2021-03-23T16:09:25.0305746Z","eventName":"UserCheckoutAcceptedIntegrationEvent"},{"actualEventTimestamp":"2021-03-23T16:09:26.0319426Z","eventName":"UserCheckoutAcceptedIntegrationEvent"},{"actualEventTimestamp":"2021-03-23T16:09:24.0303728Z","eventName":"UserCheckoutAcceptedIntegrationEvent"},{"actualEventTimestamp":"2021-03-23T16:09:28.0341688Z","eventName":"UserCheckoutAcceptedIntegrationEvent"},{"actualEventTimestamp":"2021-03-23T16:09:22.0277397Z","eventName":"UserCheckoutAcceptedIntegrationEvent"},{"actualEventTimestamp":"2021-03-23T16:09:27.032788Z","eventName":"UserCheckoutAcceptedIntegrationEvent"},{"actualEventTimestamp":"2021-03-23T16:09:23.0300894Z","eventName":"UserCheckoutAcceptedIntegrationEvent"},{"actualEventTimestamp":"2021-03-23T16:09:29.2839326Z","eventName":"OrderStatusChangedToPaidIntegrationEvent"},{"actualEventTimestamp":"2021-03-23T16:09:29.5920124Z","eventName":"OrderStatusChangedToPaidIntegrationEvent"},{"actualEventTimestamp":"2021-03-23T16:09:32.001012Z","eventName":"OrderStatusChangedToPaidIntegrationEvent"},{"actualEventTimestamp":"2021-03-23T16:09:32.3297931Z","eventName":"OrderStatusChangedToPaidIntegrationEvent"},{"actualEventTimestamp":"2021-03-23T16:09:34.3404015Z","eventName":"OrderStatusChangedToPaidIntegrationEvent"},{"actualEventTimestamp":"2021-03-23T16:09:34.574554Z","eventName":"OrderStatusChangedToPaidIntegrationEvent"},{"actualEventTimestamp":"2021-03-23T16:09:36.8421005Z","eventName":"OrderStatusChangedToPaidIntegrationEvent"},{"actualEventTimestamp":"2021-03-23T16:09:37.1583547Z","eventName":"OrderStatusChangedToPaidIntegrationEvent"},{"actualEventTimestamp":"2021-03-23T16:09:39.5765255Z","eventName":"OrderStatusChangedToPaidIntegrationEvent"},{"actualEventTimestamp":"2021-03-23T16:09:39.8544796Z","eventName":"OrderStatusChangedToPaidIntegrationEvent"},{"actualEventTimestamp":"2021-03-23T16:09:42.6338123Z","eventName":"OrderStatusChangedToPaidIntegrationEvent"},{"actualEventTimestamp":"2021-03-23T16:09:43.3090424Z","eventName":"OrderStatusChangedToPaidIntegrationEvent"},{"actualEventTimestamp":"2021-03-23T16:09:46.3397343Z","eventName":"OrderStatusChangedToPaidIntegrationEvent"},{"actualEventTimestamp":"2021-03-23T16:09:46.7209034Z","eventName":"OrderStatusChangedToPaidIntegrationEvent"},{"actualEventTimestamp":"2021-03-23T16:09:50.0028637Z","eventName":"OrderStatusChangedToPaidIntegrationEvent"},{"actualEventTimestamp":"2021-03-23T16:09:50.2646069Z","eventName":"OrderStatusChangedToPaidIntegrationEvent"},{"actualEventTimestamp":"2021-03-23T16:09:50.6301049Z","eventName":"OrderStatusChangedToPaidIntegrationEvent"},{"actualEventTimestamp":"2021-03-23T16:09:53.3695681Z","eventName":"OrderStatusChangedToPaidIntegrationEvent"},{"actualEventTimestamp":"2021-03-23T16:09:53.7303424Z","eventName":"OrderStatusChangedToPaidIntegrationEvent"},{"actualEventTimestamp":"2021-03-23T16:09:56.5492821Z","eventName":"OrderStatusChangedToPaidIntegrationEvent"},{"actualEventTimestamp":"2021-03-23T16:09:56.9011703Z","eventName":"OrderStatusChangedToPaidIntegrationEvent"},{"actualEventTimestamp":"2021-03-23T16:09:57.163438Z","eventName":"OrderStatusChangedToPaidIntegrationEvent"}]